pyrrot_wallpaper/__init__.py
pyrrot_wallpaper/config.py
pyrrot_wallpaper/wallpaper_metadata.py
pyrrot_wallpaper/wallpaper_setter.py
pyrrot_wallpaper-1.1.0.dist-info/licenses/LICENSE
pyrrot_wallpaper-1.1.0.dist-info/METADATA
pyrrot_wallpaper-1.1.0.dist-info/WHEEL
pyrrot_wallpaper-1.1.0.dist-info/entry_points.txt
pyrrot_wallpaper-1.1.0.dist-info/top_level.txt
pyrrot_wallpaper-1.1.0.dist-info/RECORD
