Metadata-Version: 2.4
Name: pyrrot_wallpaper
Version: 1.1.0
Summary: A wallpaper manager
Author-email: masuksa <author@example.com>
License:                     GNU GENERAL PUBLIC LICENSE
Project-URL: Homepage, https://github.com/masuksa/pyrrot
Project-URL: Bug Tracker, https://github.com/masuksa/pyrrot/issues
Project-URL: Gitlab, https://gitlab.com/matthias__/pyrrot
Classifier: Development Status :: 4 - Beta
Classifier: Environment :: X11 Applications
Classifier: Programming Language :: Python :: 3
Classifier: License :: OSI Approved :: GNU General Public License v3 (GPLv3)
Classifier: Operating System :: POSIX :: Linux
Classifier: Intended Audience :: End Users/Desktop
Requires-Python: >=3.7
License-File: LICENSE
Requires-Dist: pywal~=3.3
Dynamic: license-file
